ibicus/__init__.py
ibicus/__meta__.py
ibicus/variables.py
ibicus/debias/__init__.py
ibicus/debias/_cdft.py
ibicus/debias/_debiaser.py
ibicus/debias/_delta_change.py
ibicus/debias/_ecdfm.py
ibicus/debias/_isimip.py
ibicus/debias/_isimip_options.py
ibicus/debias/_linear_scaling.py
ibicus/debias/_quantile_delta_mapping.py
ibicus/debias/_quantile_mapping.py
ibicus/debias/_running_window_debiaser.py
ibicus/debias/_scaled_distribution_mapping.py
ibicus/evaluate/__init__.py
ibicus/evaluate/assumptions.py
ibicus/evaluate/correlation.py
ibicus/evaluate/marginal.py
ibicus/evaluate/metrics.py
ibicus/evaluate/multivariate.py
ibicus/evaluate/trend.py
ibicus/utils/__init__.py
ibicus/utils/_math_utils.py
ibicus/utils/_running_window_mode.py
ibicus/utils/_utils.py
ibicus-1.2.0.dist-info/licenses/LICENSE
tests/__init__.py
tests/test_cdft.py
tests/test_delta_change.py
tests/test_ecdfm.py
tests/test_handling_and_trend_preservation_all_debiasers.py
tests/test_isimip.py
tests/test_linear_scaling.py
tests/test_math_utils.py
tests/test_quantile_delta_mapping.py
tests/test_quantile_mapping.py
tests/test_running_window_mode.py
tests/test_scaled_distribution_mapping.py
tests/test_utils.py
ibicus-1.2.0.dist-info/METADATA
ibicus-1.2.0.dist-info/WHEEL
ibicus-1.2.0.dist-info/top_level.txt
ibicus-1.2.0.dist-info/RECORD
