Metadata-Version: 2.4
Name: ibicus
Version: 1.2.0
Summary: ibicus provides a flexible and user-friendly toolkit for the bias correction of climate models and associated evaluation.
Home-page: https://github.com/ecmwf-projects/ibicus
Author: Fiona Spuler, Jakob Wessel & European Centre for Medium-Range Weather Forecasts (ECMWF)
Author-email: ibicus.py@gmail.com
License: Apache License Version 2.0
Project-URL: Documentation, https://ibicus.readthedocs.io/en/latest/
Project-URL: Source, https://github.com/ecmwf-projects/ibicus
Project-URL: Tracker, https://github.com/ecmwf-projects/ibicus/issues
Classifier: Intended Audience :: Developers
Classifier: Intended Audience :: Science/Research
Classifier: Topic :: Scientific/Engineering
Classifier: Topic :: Scientific/Engineering :: Atmospheric Science
Classifier: Topic :: Scientific/Engineering :: Hydrology
Classifier: Topic :: Scientific/Engineering :: Mathematics
Classifier: Topic :: Scientific/Engineering :: Physics
Classifier: License :: OSI Approved :: Apache Software License
Classifier: Programming Language :: Python :: 3
Classifier: Programming Language :: Python :: 3.8
Classifier: Programming Language :: Python :: 3.9
Classifier: Programming Language :: Python :: 3.10
Classifier: Operating System :: OS Independent
Classifier: Development Status :: 5 - Production/Stable
Requires-Python: >=3.8
License-File: LICENSE
Requires-Dist: numpy>=1.22
Requires-Dist: attrs>=21.3.0
Requires-Dist: pandas
Requires-Dist: matplotlib
Requires-Dist: seaborn
Requires-Dist: scipy
Requires-Dist: statsmodels
Requires-Dist: scikit-learn
Requires-Dist: tqdm
Dynamic: license-file
